sphinx_shikijs/__init__.py
sphinx_shikijs/emphasizeLines.js
sphinx_shikijs/highlight.js
sphinx_shikijs-0.1.0a0.dist-info/WHEEL
sphinx_shikijs-0.1.0a0.dist-info/METADATA
sphinx_shikijs-0.1.0a0.dist-info/RECORD
