Metadata-Version: 2.1
Name: sphinx-shikijs
Version: 0.1.0a0
Summary: 
Author: Ashley Trinh
Author-email: itsashley@hey.com
Requires-Python: >=3.11,<4.0
Classifier: Programming Language :: Python :: 3
Classifier: Programming Language :: Python :: 3.11
Requires-Dist: sphinx (>=6.1.3,<7.0.0)
